{
  "_id": {
    "$oid": "67915c8af1557d68f82a641c"
  },
  "handle": "kurleebelle",
  "shortcode": "C-hofFCoVEu",
  "caption": "This duo be du-o-ing! \ud83d\ude06 Get crazy definition and long lasting moisture-shine with our Thirsty Kurls Leave-in Conditioner and Papaya Avocado Curl Milk! \ud83c\udf3a\ud83c\udf31\ud83c\udf6f\ud83e\udd51 #KurleeBelle #HairCare #NaturalHair #Curls #CurlyHair #Conditioner #LeaveinConditioner",
  "comments": 0,
  "likes": -1,
  "thumbnail": "false",
  "carouselImages": null,
  "url": "https://www.instagram.com/p/C-hofFCoVEu/",
  "video": true,
  "timestamp": 1723370452,
  "processed": true,
  "__v": 0
}