{
  "_id": {
    "$oid": "67581cbaea7651cc7fca4102"
  },
  "handle": "fashioninmagazine",
  "shortcode": "C0-BGl-tQDR",
  "caption": "\ud83e\udd23\ud83d\ude02\ud83d\ude05\ud83d\ude02 \nBy @nicocapone.comedy \n\n#funnycouple #funnycouples #funnymemes #funnyvideos #couplegoals #couplevideos #couple #fun #funny #memes #funnyshit #couplememe #viral #viralpost #married #marriedlife #marriedcouple",
  "comments": 144,
  "likes": -1,
  "thumbnail": "false",
  "carouselImages": null,
  "url": "https://www.instagram.com/p/C0-BGl-tQDR/",
  "video": true,
  "timestamp": 1702848089,
  "processed": true,
  "__v": 0
}