{
  "_id": {
    "$oid": "67581ca6ea7651cc7fca40c1"
  },
  "handle": "fashioninmagazine",
  "shortcode": "C20xUy_tA2H",
  "caption": "\ud83e\udd23\ud83e\udd23\ud83d\ude05 \nBy @robsyman @nicocapone.comedy \n \n \n\n#funnycouple #funnycouples #funnymemes #funnyvideos #couplegoals #couplevideos #couple #fun #funny #memes #funnyshit #couplememe #viral #viralpost #married #marriedlife #marriedcouple #reel #reels #reelitfeelit #viralreels #viralreel #instareels #reelsinstagram",
  "comments": 120,
  "likes": -1,
  "thumbnail": "false",
  "carouselImages": null,
  "url": "https://www.instagram.com/p/C20xUy_tA2H/",
  "video": true,
  "timestamp": 1706832777,
  "processed": true,
  "__v": 0
}