{
  "_id": {
    "$oid": "67581ca0ea7651cc7fca40ba"
  },
  "handle": "fashioninmagazine",
  "shortcode": "C3D_g4jtbaP",
  "caption": "#ladygaga & #bradleycooper \u2665\ufe0f What do you think of them?\n \ud83c\udf1f\n\n#reel #reels #reelsinstagram #celebrity #celebrities #explore #explorepage #exploremore #explorepage\u2728 #reelsvideo #viralreels #reelsinstagram #reelsinsta #reelsviral #reelsvideo #reelslovers #trendingreels #trendingreel",
  "comments": 67,
  "likes": -1,
  "thumbnail": "false",
  "carouselImages": null,
  "url": "https://www.instagram.com/p/C3D_g4jtbaP/",
  "video": true,
  "timestamp": 1707343764,
  "processed": true,
  "__v": 0
}