{
  "_id": {
    "$oid": "681e6e934094574e21eabcb6"
  },
  "handle": "furrylicious",
  "shortcode": "C5JFbh0Oyaa",
  "caption": "Meet Summer, our stunning Mini Poodle\ud83d\udc95 She is hypoallergenic, and will only be about 12lbs fully grown. Come on in to meet this cutie today!\ud83d\udc36For more information, you can call or text us at 908-823-4469 \ud83d\udcde We can also be reached via email info@furrylicious.com , or through instagram and facebook messages \ud83d\udc8c  #whitehousestationnj #nj #newjersey #puppies #cute #minipoodle",
  "comments": 0,
  "likes": 190,
  "thumbnail": "false",
  "carouselImages": null,
  "url": "https://www.instagram.com/p/C5JFbh0Oyaa/",
  "video": false,
  "timestamp": 1711809333,
  "processed": true,
  "__v": 0
}