{
  "_id": {
    "$oid": "682864b2426c08e47665daff"
  },
  "handle": "connectrnapp",
  "shortcode": "C6oaiicuyAv",
  "caption": "This year for nurses week, we recognize that work life balance is so hard for so many nurses. We understand you need to put your life first so you can thrive on and off the shift. \n\nWe\u2019re excited to announce a giveaway at the end of the week that supports this idea, and helps you be the best person and nurse you can be. Stay tuned! \n\n#nursesweek2024 #nursegiveaway #nursesofinstagram #nursesofig #nurselife #nurseweekgiveaway",
  "comments": 10,
  "likes": -1,
  "thumbnail": "false",
  "carouselImages": null,
  "url": "https://www.instagram.com/p/C6oaiicuyAv/",
  "video": true,
  "timestamp": 1715008113,
  "processed": true,
  "__v": 0
}