{
  "_id": {
    "$oid": "682667b2b8bf82966661033a"
  },
  "handle": "aimeejoelleziering",
  "shortcode": "C7IX6U_Rdwf",
  "caption": "\u201cThe Becoming of a Woman\u201d Oil painting on canvas of my beautiful soul sister friend, whom I tried to capture \ud83e\udd8b @michelle.hochberg \nIt is a beautiful thing to be in the presence of someone ever evolving with love and wisdom \u2728 \ud83c\udf3c \ud83e\ude77 #originaloilpainting #oilportraitpainting #divinefeminineawakening",
  "comments": 147,
  "likes": -1,
  "thumbnail": "false",
  "carouselImages": [
    false,
    false,
    false,
    false,
    false
  ],
  "url": "https://www.instagram.com/p/C7IX6U_Rdwf/",
  "video": false,
  "timestamp": 1716080435,
  "processed": true,
  "__v": 0
}