{
  "_id": {
    "$oid": "681e6e614094574e21eabc4c"
  },
  "handle": "furrylicious",
  "shortcode": "C8pZYwdJl9f",
  "caption": "Meet Bubbles and Niko our Shorkie puppies!\u2764\ufe0fThese cuties are a cross between a Shih Tzu and a Yorkshire Terrier making them hypoallergenic. They are estimated to be about 10lbs fully grown. Come on in to meet them to see their curious, playful personalities at firsthand! Our doors are always open 11-7\ud83d\udc36 For more information, you can call or text us at 908-823-4469 \ud83d\udcde We can also be reached via email info@furrylicious.com , or through instagram and facebook messages \ud83d\udc8c  #whitehousestationnj #nj #newjersey #puppies #cute #shorkie #shorkiepuppy",
  "comments": 0,
  "likes": -1,
  "thumbnail": "false",
  "carouselImages": null,
  "url": "https://www.instagram.com/p/C8pZYwdJl9f/",
  "video": false,
  "timestamp": 1719335989,
  "processed": true,
  "__v": 0
}