{
  "_id": {
    "$oid": "6828c95a9f749c549fe3d66c"
  },
  "handle": "hoka",
  "shortcode": "C9C80l4pfT1",
  "caption": "From Olympic Valley to Auburn, California, HOKA athletes turned out fearless performances at the 2024 Western States Endurance Run. On Saturday night at Placer High School, six runners claimed top 10 finishes in the men\u2019s and women\u2019s 100-mile race.\n\nFind our full race recap through the link in our profile \ud83d\udd17\n\n#WesternStates #WSER #HOKA #FlyHumanFly\n\nVideo: @rhoamcreative.studio",
  "comments": 12,
  "likes": 844,
  "thumbnail": "false",
  "carouselImages": null,
  "url": "https://www.instagram.com/p/C9C80l4pfT1/",
  "video": true,
  "timestamp": 1720195257,
  "processed": true,
  "__v": 0
}