{
  "_id": {
    "$oid": "67ef7c2fa3f539ca051417c0"
  },
  "handle": "savorbysuzie",
  "shortcode": "C_jbLLdvxjm",
  "caption": "We\u2019re game to be the MVP (most valuable pretzel) of this football season \ud83c\udfc8\ud83e\udd68\ud83d\ude01\n\nWho\u2019s ready for the NFL kickoff?!",
  "comments": 3,
  "likes": 30,
  "thumbnail": "false",
  "carouselImages": null,
  "url": "https://www.instagram.com/p/C_jbLLdvxjm/",
  "video": true,
  "timestamp": 1725578077,
  "processed": true,
  "__v": 0
}