{
  "_id": {
    "$oid": "673c6156515f384a7faa9dbb"
  },
  "handle": "pageneralstore",
  "shortcode": "C_TJvBnJjBC",
  "caption": "Sweet treats! Kouign Amann (Sat/Sun)+ canel\u00e9s (Sat only) at our @rdgterminalmkt store! + much more. Stop by early -they go quick! (we open at 8am)\n\nMake a morning of it! Pick up fresh @metropolitanbakery bread, and peruse our abundant selection of PA made specialty foods and wares + shop all of the other amazing small businesses in the market! \n\n#phillyfood #phillyfoodie #philadelphiafood #philadelphia_citylife #philadelphiafoodie #philadelphiafoodies #phillyeats #phillyeatsgood #phillysweets #phillygram #shoplocalsupportlocal #independentgrocer #pastrylove #phillycooks #pennsylvaniafoodie #visitphilly #thingstodoinphilly #weekendvibes #foodporn #readingterminalmarket #centercityphilly #centercityphiladelphia #phillysupportphilly",
  "comments": 0,
  "likes": 15,
  "thumbnail": "false",
  "carouselImages": null,
  "url": "https://www.instagram.com/p/C_TJvBnJjBC/",
  "video": true,
  "timestamp": 1725033317,
  "processed": true,
  "__v": 0
}