{
  "_id": {
    "$oid": "67a5faf730e8e7428cd80fc0"
  },
  "handle": "indigoreinjeans",
  "shortcode": "CEe0dk0jnzD",
  "caption": "You will get there but only if you keep going\u2728 \ud83d\udcf8 photo cred @asifvint \n.\n.\n#indigoreinjeans #indigoreindenim #thinkgreenwearblue #sustainable #repreve #reprevefabric #denimlover #lovedenim #denim #denimjeans #destruction #mending #destructedjeans #vintagefeeling #acidwash #lightwashjeans #bestseller #bestwash #destructionpatterns #anotherhappyircustomer #keepgrowing #keepgoing #courdoroy #courdoroyskirt #indigoreinskirt",
  "comments": 1,
  "likes": 28,
  "thumbnail": "false",
  "carouselImages": null,
  "url": "https://www.instagram.com/p/CEe0dk0jnzD/",
  "video": false,
  "timestamp": 1598722001,
  "processed": true,
  "__v": 0
}