{
  "_id": {
    "$oid": "67a5faf430e8e7428cd80faf"
  },
  "handle": "indigoreinjeans",
  "shortcode": "CGV2N3JsGPk",
  "caption": "The perfect fall outfit in our eyes: a cozy jacket and the perfect pairing of your favorite Indigo Rein jeans!\n\ud83d\udcf8 photo cred @sam_bakies \n.\n.\n.\n#indigoreinjeans #indigoreindenim #thinkgreenwearblue #sustainable #repreve #reprevefabric #denimlover #lovedenim #denim #denimjeans #destruction #mending #destructedjeans #vintagefeeling #acidwash #lightwashjeans #bestseller #cozy  #fallvibes #pumpkinspice #anotherhappyIRcustomer #mediumwash #wfhoutfit #nyc #nycdenim",
  "comments": 3,
  "likes": 27,
  "thumbnail": "false",
  "carouselImages": null,
  "url": "https://www.instagram.com/p/CGV2N3JsGPk/",
  "video": false,
  "timestamp": 1602715898,
  "processed": true,
  "__v": 0
}