{
  "_id": {
    "$oid": "67a5faf130e8e7428cd80fa4"
  },
  "handle": "indigoreinjeans",
  "shortcode": "CJWRD0ksjlx",
  "caption": "perfect winter outfit essentials\u2728\n\ncozy sherpa, comfy sneakers, cute accessories and your favorite pair of Indigo Rein jeans\ud83d\udc4f\ud83c\udffb\n.\n.\n.\n#happyholidays #holidayoutfit #destructeddenim  #distressed #indigorein #indigoreinjeans #holidayseason #holiday #dreamer #holidaytime #indigorein #indigoreinjeans #indigoreindenim #thinkgreenwearblue #sustainable #repreve #reprevefabric #denimlover #lovedenim #denim #denimjeans #destruction #destructedjeans #vintagefeeling #bestseller #merryxmas #anotherhappyIRcustomer #mediumwash #hellodecember",
  "comments": 1,
  "likes": 32,
  "thumbnail": "false",
  "carouselImages": null,
  "url": "https://www.instagram.com/p/CJWRD0ksjlx/",
  "video": false,
  "timestamp": 1609172423,
  "processed": true,
  "__v": 0
}