{
  "_id": {
    "$oid": "68292a83f5ce7630fc0abf0b"
  },
  "handle": "kyonathelawyer",
  "shortcode": "ClKY0TVDLFl",
  "caption": "Send this to all the wives \ud83d\ude0e\u270a\ud83c\udffe.\n\nWho will (politely) send the food back if we don\u2019t?! \ud83e\udd23\n\n#TrademarkLawyer  #SmallBusiness #Lawyer",
  "comments": 46,
  "likes": 863,
  "thumbnail": "false",
  "carouselImages": null,
  "url": "https://www.instagram.com/p/ClKY0TVDLFl/",
  "video": true,
  "timestamp": 1668903526,
  "processed": true,
  "__v": 0
}