{
  "_id": {
    "$oid": "673c61e4515f384a7faa9f1b"
  },
  "handle": "pageneralstore",
  "shortcode": "Cpxh4GZu85h",
  "caption": "HAPPY PI DAY!\nSave $3.14 on all of our pies \ud83d\ude0a\nSale ends TODAY \u2014 only on pageneralstore.com! \n\n#piday #math #mathnerd #mathiscool #tastykake #whoopiepie",
  "comments": 0,
  "likes": 8,
  "thumbnail": "false",
  "carouselImages": null,
  "url": "https://www.instagram.com/p/Cpxh4GZu85h/",
  "video": false,
  "timestamp": 1678806686,
  "processed": true,
  "__v": 0
}