{
  "_id": {
    "$oid": "6842e9e4c037254af0991b7d"
  },
  "handle": "cats.and.bows",
  "shortcode": "Ctb7B1XoEf6",
  "caption": "BOW STYLING 101 \ud83c\udf80\ud83d\ude0d\ud83d\ude01\nShop link in bio \u2728\n.\n.\n.\nDress : @panila_westernedit \n.\n.\n#bows #bowclips #hairbows #explore #exploremore #viralreel #hairbowclip #clipbows #bowclips #supportindiandesigners #shoplocal",
  "comments": 18,
  "likes": 244,
  "thumbnail": "false",
  "carouselImages": null,
  "url": "https://www.instagram.com/p/Ctb7B1XoEf6/",
  "video": true,
  "timestamp": 1686671865,
  "processed": true,
  "__v": 0
}