{
  "_id": {
    "$oid": "682688296453fed3b524ef7f"
  },
  "handle": "alikaynaturals",
  "shortcode": "CyOdhliMccc",
  "caption": "@saricurls has everything you need to get your hair right! #AlikayNaturals only uses premium and quality ingredients in each product. \n\nShop @alikaynaturals on shelf and ask for @serpil.saricurls, at her location at: GmbH Zeppelinstr. 1, 68519 Viernheim, Germany. \ud83c\udf3a\n\nAnd Happy Belated Birthday @serpil.saricurls! We hope you enjoyed your special day! \ud83e\uddc1\ud83e\udd42\ud83c\udf7e\u2728",
  "comments": 3,
  "likes": -1,
  "thumbnail": "false",
  "carouselImages": [
    false
  ],
  "url": "https://www.instagram.com/p/CyOdhliMccc/",
  "video": false,
  "timestamp": 1696957354,
  "processed": true,
  "__v": 0
}