{
  "_id": {
    "$oid": "6825b0fd5ff8a89f234ec7be"
  },
  "handle": "bombaybrowbar",
  "shortcode": "CZDab5KtCAf",
  "caption": "There's nothing that lights us up more than receiving positive reviews! \ud83d\ude0d Thank you so much for those kind words. \u2728\ud83d\udc95\n\nWant to leave a review too? Head to our Stories for more information. \ud83e\udd70",
  "comments": 2,
  "likes": 25,
  "thumbnail": "false",
  "carouselImages": null,
  "url": "https://www.instagram.com/p/CZDab5KtCAf/",
  "video": false,
  "timestamp": 1642899545,
  "processed": true,
  "__v": 0
}