{
  "_id": {
    "$oid": "6729ee694d9886be051a985c"
  },
  "handle": "volvocarsrochester",
  "shortcode": "DB0IViUOb45",
  "caption": "CONGRATS! Tresia just purchased a new Volvo XC60 Recharge. We hope you enjoy your new vehicle and thank you for choosing our dealership!\r\n - Alexandria Erickson\r\nShop Vehicles Now: https://www.volvocarsrochester.com/",
  "comments": 0,
  "likes": 1,
  "thumbnail": "false",
  "carouselImages": null,
  "url": "https://www.instagram.com/p/DB0IViUOb45/",
  "video": false,
  "timestamp": 1730433568,
  "processed": true,
  "__v": 0
}