{
  "_id": {
    "$oid": "6842945cac1e1202415f22e1"
  },
  "handle": "drunkelephant",
  "shortcode": "DB12GrJABiB",
  "caption": "It\u2019s officially @Sephora Season. For all you Beauty Insider members, the Sephora Savings Event is here! \n \nWHAT? \n- Rouge: 20% off \n- VIB: 15% off\n- Insider: 10% off\n \nWHEN? \n- Rouge: Nov. 1-11\n- VIB: Nov. 1-11\n- Insider: Nov. 5-11\n \nWHERE? \nIn store and online.\n \nHOW? \nUse code SAVINGS at checkout.",
  "comments": 27,
  "likes": 1163,
  "thumbnail": "false",
  "carouselImages": null,
  "url": "https://www.instagram.com/p/DB12GrJABiB/",
  "video": true,
  "timestamp": 1730491145,
  "processed": true,
  "__v": 0
}