{
  "_id": {
    "$oid": "672978e916cbdc0376d991e7"
  },
  "handle": "pgatour",
  "shortcode": "DB1OkK1OJbP",
  "caption": "The pros got into the Halloween spirit \ud83c\udf83\ud83d\udc7b",
  "comments": 345,
  "likes": 66671,
  "thumbnail": "false",
  "carouselImages": [
    false,
    false,
    false,
    false,
    "https://ag-images.s3.amazonaws.com/pgatour/465240399_423418890596513_437704342567872132_n.jpg",
    "https://ag-images.s3.amazonaws.com/pgatour/465298860_1252313245978136_6813910451628950062_n.jpg",
    "https://ag-images.s3.amazonaws.com/pgatour/465073159_925557562772080_3245809380955959763_n.jpg",
    "https://ag-images.s3.amazonaws.com/pgatour/465059494_567248579022023_8620211882565380811_n.jpg"
  ],
  "url": "https://www.instagram.com/p/DB1OkK1OJbP/",
  "video": false,
  "timestamp": 1730470387,
  "processed": true,
  "__v": 0
}