{
  "_id": {
    "$oid": "6827bdc3c8fe470cb5834363"
  },
  "handle": "forfive",
  "shortcode": "DB4LMj1PN6u",
  "caption": "Once you try it once, you won\u2019t stop thinking about it. \ud83e\udd24\n\nMy absolute favorite sandwich from @forfive \nTheir chicken Caesar sandwich is a game changer. \n\n\ud83d\udccd @forfive \nGarden City, NY \n\n\ud83c\udf1f follow @whatsnikkyeating for more delicious recommendations \ud83d\ude0c\n\n#chickencaesar #chickencaesarsalad #chickencaesarsandwich #sandwich #forfive #nyceeeeeats #longislandfoodie #longislandeats",
  "comments": 18,
  "likes": 232,
  "thumbnail": "false",
  "carouselImages": null,
  "url": "https://www.instagram.com/p/DB4LMj1PN6u/",
  "video": false,
  "timestamp": 1730569284,
  "processed": true,
  "__v": 0
}