{
  "_id": {
    "$oid": "6729d96e73c11cc06da195dc"
  },
  "handle": "toniandguyworld",
  "shortcode": "DB6s6v6iWTu",
  "caption": "Which colour is your favourite? 1 or 2?\ud83e\udd8b\ud83c\udf4a\n\n.\n\u26a1@breakthroughteam\n.\n.\n#ToniAndGuy #ToniAndGuyWorld #bluehair #orangehair #vividhaircolour #vividhairgoals #brighthair #hairideas #hairtransformation #beforeandafterhair #hairinspiration #hairinspired #creativecoloring #creativehair #pinkhairinspo #faceframe #hairsalon #haireducation #haireducator #waveyhair #colourpainting #hairpainting #brighthaircolour",
  "comments": 7,
  "likes": 642,
  "thumbnail": "false",
  "carouselImages": [
    false
  ],
  "url": "https://www.instagram.com/p/DB6s6v6iWTu/",
  "video": false,
  "timestamp": 1730654072,
  "processed": true,
  "__v": 0
}