{
  "_id": {
    "$oid": "6784a796ac6407e452ae4495"
  },
  "handle": "digital_marketing_nomad",
  "shortcode": "DB_UwrHOhUC",
  "caption": "Learn the 2 hour work day and make daily \ud83d\udcb0! \nImagine wakinging up to \ud83d\udcb0 in your bank account what would that mean for you and your family? For me it means I no longer work a 9-5, I can stay home with my kids and do whatever we feel like doing! Inside the Legacy Builder you get access to a live mentorship and a community of people who will help you succeed! This is NOT just another course it is LiFE CHANGING! The Legacy Builder has completely changed my life and It can change yours too! Get started today! Feel free to reach out If you have any questions I am here to answer them! \n\n#Marketing, #SEO, #SocialMedia, #SocialEntrepreneurship, #Advertisement, #MarketingAndAdvertising, #MarketingCommunications, #Branding, #Storytelling, #SocialNetworking, #MobileMarketing, and #Website",
  "comments": 0,
  "likes": 0,
  "thumbnail": "false",
  "carouselImages": null,
  "url": "https://www.instagram.com/p/DB_UwrHOhUC/",
  "video": true,
  "timestamp": 1730809941,
  "processed": true,
  "__v": 0
}