{
  "_id": {
    "$oid": "6828c9459f749c549fe3d60c"
  },
  "handle": "hoka",
  "shortcode": "DBbyMCFPgL0",
  "caption": "Her competitors called her, \u201cOne of the greatest we\u2019ve ever seen.\u201d As we wish 5x @ironmantri World Champion @danielaryf a happy retirement from pro triathlon, we spoke with some of the sports other greatest athletes who shared their memories of racing with her. Watch the full film through the link in our profile. \n\n#IRONMAN #Triathlon #IRONMANtri",
  "comments": 34,
  "likes": 3060,
  "thumbnail": "false",
  "carouselImages": null,
  "url": "https://www.instagram.com/p/DBbyMCFPgL0/",
  "video": true,
  "timestamp": 1729616806,
  "processed": true,
  "__v": 0
}