{
  "_id": {
    "$oid": "6729f46a52d804619249227f"
  },
  "handle": "wellnesslivingsoftware",
  "shortcode": "DBy89htJ8jm",
  "caption": "Stop ignoring your finances & sales numbers. \ud83d\uded1 \n\nLearn quick tips for analyzing important reports! \n\nCatch the replay of our latest WellnessLiving Academy session now. \ud83d\udd17 Link in bio. \n\n#WellnessLivingAcademy #FinancialWellness #WellnessLivingSoftware",
  "comments": 0,
  "likes": 0,
  "thumbnail": "false",
  "carouselImages": null,
  "url": "https://www.instagram.com/p/DBy89htJ8jm/",
  "video": false,
  "timestamp": 1730394052,
  "processed": true,
  "__v": 0
}