{
  "_id": {
    "$oid": "671e0656a0365048d7af82b6"
  },
  "handle": "thebettergeneration",
  "shortcode": "DBZ116BsOn1",
  "caption": "TBG X New Era Thermal Nightmare Halloween Pack\n\nWelcome to our Halloween Night Thermal Pack Astros Kit. A nightmare in the flesh, these are brought to life during the day and shows their true colors at night through a color shifting heat reactive upper. These New Era & TBG fitted bring the halloween spirit to life with the latest tech. Each fitted changes colors depending on the temperature for a truly 1-of-1 experience. Available on 10.25 at 9:00 PM CST Online for $55. \n\nNew Era X TBG Houston Astros Fitted Thermal Nightmare \u201cJack-O-Latern\u201d\nSizes 6 7/8 - 7 5/8\n\nNew Era X TBG Houston Astros Fitted Thermal Nightmare \u201cGoblin\u201d\nSizes 6 7/8 - 7 3/4 \n\nNew Era X TBG Houston Astros Fitted Thermal Nightmare \u201cGhoul\u201d\nSizes 7 - 7 3/4",
  "comments": 9,
  "likes": 260,
  "thumbnail": "false",
  "carouselImages": [
    false,
    false
  ],
  "url": "https://www.instagram.com/p/DBZ116BsOn1/",
  "video": false,
  "timestamp": 1729551455,
  "processed": true,
  "__v": 0
}