{
  "_id": {
    "$oid": "68282df36a44944dc30c85b8"
  },
  "handle": "padsplit",
  "shortcode": "DCmVuVEv2ei",
  "caption": "Our members are at the heart of everything we do. Their stories of hope, resilience, and growth inspire us every day\u2014and we\u2019re honored to share them with you. Here\u2019s to the journeys, the dreams, and the power of lifting each other up. \ud83c\udf1f\n\n#AffordableHousing #Coliving #PadSplit",
  "comments": 0,
  "likes": 20,
  "thumbnail": "false",
  "carouselImages": [
    false,
    false,
    false,
    false
  ],
  "url": "https://www.instagram.com/p/DCmVuVEv2ei/",
  "video": false,
  "timestamp": 1732118307,
  "processed": true,
  "__v": 0
}