{
  "_id": {
    "$oid": "6839769dea2253e7d1603631"
  },
  "handle": "foxterradesign",
  "shortcode": "DDIiCdBuVqN",
  "caption": "\ud83d\udea8 Don\u2019t wait\u2014start NOW! \ud83d\udea8\nTransforming your dream yard into reality takes time, but the journey is worth it. Here\u2019s what it takes:\n1\ufe0f\u20e3 Plan your budget\u20282\ufe0f\u20e3 Hire a design firm\u20283\ufe0f\u20e3 Collaborate on the perfect design\u20284\ufe0f\u20e3 Get bids from top contractors\u20285\ufe0f\u20e3 Secure necessary permits\u20286\ufe0f\u20e3 Begin construction (3-10 months!)\n\u2728 Pro Tip: Starting today means your backyard oasis will be ready by next summer! \u2728\nDon\u2019t wait until it\u2019s too late\u2014let\u2019s bring your vision to life. DM us or click the link in our bio to get started! \ud83c\udf3f\ud83d\udca6 #DreamYard #LandscapeDesign #BackyardGoals",
  "comments": 4,
  "likes": 163,
  "thumbnail": "false",
  "carouselImages": [
    false,
    false,
    false,
    false,
    false,
    false
  ],
  "url": "https://www.instagram.com/p/DDIiCdBuVqN/",
  "video": false,
  "timestamp": 1733265614,
  "processed": true,
  "__v": 0
}