{
  "_id": {
    "$oid": "682728197888b96cbe4e9757"
  },
  "handle": "thegoodquote",
  "shortcode": "DELc5OxIAdy",
  "caption": "\ud83d\udd25 GET FEATURED \ud83d\udd25 \u2014 Share the most valuable lesson you\u2019ve learned in 2024 in the comments below. Drop your best advice, and we\u2019ll turn it into a quote and tag you. It must be an original quote, we will double check. \ud83c\udf3b",
  "comments": 1397,
  "likes": 14070,
  "thumbnail": "false",
  "carouselImages": null,
  "url": "https://www.instagram.com/p/DELc5OxIAdy/",
  "video": false,
  "timestamp": 1735511065,
  "processed": true,
  "__v": 0
}