{
  "_id": {
    "$oid": "6792332df65b56202b666092"
  },
  "handle": "natgeo",
  "shortcode": "DEum_9HgDb9",
  "caption": "More people have been to the surface of the moon than these caves. The speleothems hidden within might hold the key to understanding what Greenland's climate was like in the past. Learn more at the link in bio.\n\nHost: @expedition_doctor\nVideo by: @shonephoto and @expedition_doctor",
  "comments": 155,
  "likes": 47198,
  "thumbnail": "false",
  "carouselImages": null,
  "url": "https://www.instagram.com/p/DEum_9HgDb9/",
  "video": true,
  "timestamp": 1736690823,
  "processed": true,
  "__v": 0
}