{
  "_id": {
    "$oid": "67c1fcd497ed90480c1f86f0"
  },
  "handle": "drinkmilos",
  "shortcode": "DF5l9VxvJt_",
  "caption": "Roses are red, violets are blue, Valentine\u2019s Day is sweeter with Milo\u2019s and you. \ud83d\udc95 Reminder to stock up on Milo's to make this #ValentinesDay even sweeter!",
  "comments": 21,
  "likes": 373,
  "thumbnail": "false",
  "carouselImages": null,
  "url": "https://www.instagram.com/p/DF5l9VxvJt_/",
  "video": false,
  "timestamp": 1739206809,
  "processed": true,
  "__v": 0
}