{
  "_id": {
    "$oid": "681e7ba93ed5334c48127a6d"
  },
  "handle": "juna.world",
  "shortcode": "DF9Nzjyxezn",
  "caption": "self care = self love \ud83e\udd0d every little act of self care is a love letter to yourself \u2728\n\n#selflove #wellness #guthealth #healthylifestyle #wellnessjourney #reels",
  "comments": 3,
  "likes": -1,
  "thumbnail": "false",
  "carouselImages": null,
  "url": "https://www.instagram.com/p/DF9Nzjyxezn/",
  "video": true,
  "timestamp": 1739328482,
  "processed": true,
  "__v": 0
}