{
  "_id": {
    "$oid": "67c24b3bfebd2176c850f881"
  },
  "handle": "hollyhuntdesign",
  "shortcode": "DGA_wMxRPRI",
  "caption": "@autumn_elizabeth_design brings elevated comfort to this private aircraft with a luxurious banquette upholstered in our Mademoiselle: Shadow textile.\n\nPhoto: @ashlee_hamon_photography\n\n#HOLLYHUNT #LuxuryInteriors #Textiles",
  "comments": 4,
  "likes": 199,
  "thumbnail": "false",
  "carouselImages": [
    false,
    false,
    false,
    false
  ],
  "url": "https://www.instagram.com/p/DGA_wMxRPRI/",
  "video": false,
  "timestamp": 1739455212,
  "processed": true,
  "__v": 0
}