{
  "_id": {
    "$oid": "67c346602d9e1393301e54d2"
  },
  "handle": "shawn_marshall_art",
  "shortcode": "DGica3duvlB",
  "caption": "\u201cStamina\u201d | Collage on Panel.\n.\n.\n.\n#collage #kolaj #moderncollage #collagist #contemporaryart #contemporarycollage #analogcollage #papercollage #cutandpaste #cutandpastecollage #photocollage #pariscollagecollective #collagecollective #loveanalogcollage1 #collagecommunity #mixedmediacollage #assemblage #handmade #hand #cut #upcycled #paper",
  "comments": 0,
  "likes": 30,
  "thumbnail": "false",
  "carouselImages": [
    false,
    false
  ],
  "url": "https://www.instagram.com/p/DGica3duvlB/",
  "video": false,
  "timestamp": 1740577534,
  "processed": true,
  "__v": 0
}