{
  "_id": {
    "$oid": "67c1eb41efb2749142201692"
  },
  "handle": "davinesnorthamerica",
  "shortcode": "DGV5F3cRQc8",
  "caption": "Treat yourself to a luxurious and relaxing salon self-care day \ud83e\udd29\n\nOur OI range is designed for all hair types. If you have medium or thick hair, your product lineup may differ from someone with a different hair type. However, the one constant for everyone is OI Souffl\u00e9.\n\nHow you\u2019ll know? Leave it to the professionals - Our stylists will have you leaving the salon with a routine that is catered to your hair needs. Link in bio \ud83d\udda4\n\n#daivnes #sustainablebeauty",
  "comments": 2,
  "likes": -1,
  "thumbnail": "false",
  "carouselImages": null,
  "url": "https://www.instagram.com/p/DGV5F3cRQc8/",
  "video": true,
  "timestamp": 1740156398,
  "processed": true,
  "__v": 0
}