{
  "_id": {
    "$oid": "6825212924e0fbf656b2d4d6"
  },
  "handle": "instatroll_football",
  "shortcode": "DH-y67xMaAO",
  "caption": "Real Madrid have WON three times as many Champions League trophies as Copa del Rey Titles since 2014! \ud83c\udfc6\ud83d\ude31\n\nThey have also played in twice as many UCL finals as CDR finals over the last decade! \n\nFor context, the Copa del Rey features teams from all Spanish divisions, while the Champions League brings together the best clubs in Europe.\n\nJust Real Madrid things! \ud83d\ude02",
  "comments": 273,
  "likes": 64285,
  "thumbnail": "false",
  "carouselImages": null,
  "url": "https://www.instagram.com/p/DH-y67xMaAO/",
  "video": false,
  "timestamp": 1743676339,
  "processed": true,
  "__v": 0
}