{
  "_id": {
    "$oid": "67ef8666659cdb6bbb091c3c"
  },
  "handle": "gopro",
  "shortcode": "DH33ykRJ9MQ",
  "caption": "Photo of the Day: Right place, right time \ud83c\udf04 Shot on HERO13 Black by #GoProFamily member @sara800114 in the naturally carved caves of Page, AZ.\n\n#GoPro #GoProHERO13 #Arizona #Desert #LandscapePhotography",
  "comments": 42,
  "likes": 12465,
  "thumbnail": "false",
  "carouselImages": null,
  "url": "https://www.instagram.com/p/DH33ykRJ9MQ/",
  "video": false,
  "timestamp": 1743444015,
  "processed": true,
  "__v": 0
}