{
  "_id": {
    "$oid": "680b326e0cbac07187ceb246"
  },
  "handle": "barilla",
  "shortcode": "DH5oPWXNZiE",
  "caption": "Introducing: Barilla Cereali\n\nBecause why should pasta be limited to only lunch and dinner? \n\nThe ultimate breakfast innovation: crunchy, al dente farfalle, with a creamy, cheesy flavour. It\u2019s the breakfast you never knew you needed \u2013 just add hot milk!\n\n#BarillaCereali #aprilfools #aprilfoolsday",
  "comments": 224,
  "likes": 21665,
  "thumbnail": "false",
  "carouselImages": null,
  "url": "https://www.instagram.com/p/DH5oPWXNZiE/",
  "video": false,
  "timestamp": 1743502970,
  "processed": true,
  "__v": 0
}