{
  "_id": {
    "$oid": "67ef9cf6242f230dc3e1dcc8"
  },
  "handle": "jasonmarkk",
  "shortcode": "DH9h_1VMH2u",
  "caption": "Odorless, colorless and PFAS Free. Our water-based formula creates a durable, breathable barrier that protects your shoes from accidental spills or inclement weather.",
  "comments": 2,
  "likes": -1,
  "thumbnail": "false",
  "carouselImages": [
    false,
    false,
    false
  ],
  "url": "https://www.instagram.com/p/DH9h_1VMH2u/",
  "video": false,
  "timestamp": 1743633914,
  "processed": true,
  "__v": 0
}