{
  "_id": {
    "$oid": "681e0a251e88db2908a489d0"
  },
  "handle": "scriptedfragrance",
  "shortcode": "DH9VGSvygS3",
  "caption": "Are you a candle lover looking for unbeatable deals on high-quality, handcrafted candles? \ud83d\udd6f\ufe0f\u2600\ufe0f\ud83e\udd0d\n\nThen you won\u2019t want to miss our exclusive Warehouse Sale in Warwick, New York this Saturday, April 5th from 10a - 4p at our historic studio. \n\nThis is your chance to shop our \u2018less than perfect\u2019 candles at DEEP discounts\u2014up to 90% off\u2014and bring home beautifully scented soy candles that burn flawlessly but may have minor cosmetic flaws, incomplete packaging, or are simply discontinued.\n\nLooking to ensure you get the BEST selection? RSVP to become a VIP and shop early at 9:30a!\n\nBe sure to share with a friend and visit our \ud83d\udd17 in bio for all event and RSVP details \u2728",
  "comments": 0,
  "likes": 26,
  "thumbnail": "false",
  "carouselImages": [
    false
  ],
  "url": "https://www.instagram.com/p/DH9VGSvygS3/",
  "video": false,
  "timestamp": 1743627149,
  "processed": true,
  "__v": 0
}