{
  "_id": {
    "$oid": "6828685e8d0192526f7bd684"
  },
  "handle": "enzozelocchi",
  "shortcode": "DH__BQARDof",
  "caption": "\u201cSmall opportunities are often the beginning of great enterprises.. Wait for the wisest of all counselors, time\u201d. #enzozelocchi #love",
  "comments": 0,
  "likes": 1326411,
  "thumbnail": "false",
  "carouselImages": [
    false
  ],
  "url": "https://www.instagram.com/p/DH__BQARDof/",
  "video": false,
  "timestamp": 1743716237,
  "processed": true,
  "__v": 0
}