{
  "_id": {
    "$oid": "67d93fb53fd36dec45bf9f2a"
  },
  "handle": "jooliesdates",
  "shortcode": "DHB9DHGJACz",
  "caption": "\ud83d\ude0dLOVESTRUCK at the Date-ing Booth\ud83d\udc98\n\nWe came, we date-ed, and we left with all the snacks\ud83d\ude1c Thank you to everyone who stopped by for a date and made this expo even greater (and sweeter!) than the last\u2763\ufe0f",
  "comments": 61,
  "likes": 221,
  "thumbnail": "false",
  "carouselImages": null,
  "url": "https://www.instagram.com/p/DHB9DHGJACz/",
  "video": true,
  "timestamp": 1741634867,
  "processed": true,
  "__v": 0
}