{
  "_id": {
    "$oid": "682786cada573b77953eb22e"
  },
  "handle": "pureandsimpleca",
  "shortcode": "DHgc8WLuoPR",
  "caption": "Q + A with Pure + Simple Founder, Jean: Common skin health misconceptions. You\u2019ve trusted us for 25 years to create natural products tailored to your skin\u2019s needs: our team is here to combat your acne concerns.",
  "comments": 0,
  "likes": -1,
  "thumbnail": "false",
  "carouselImages": null,
  "url": "https://www.instagram.com/p/DHgc8WLuoPR/",
  "video": true,
  "timestamp": 1742658277,
  "processed": true,
  "__v": 0
}