{
  "_id": {
    "$oid": "67d96145c0e0f9520d18528c"
  },
  "handle": "versus",
  "shortcode": "DHTLkeXNGc6",
  "caption": "Ebony Salmon is one of the most exciting ballers in the Barclays WSL. With razor-sharp feet and sprint speed that puts her among the fastest players in the game, she\u2019s got all the attributes needed to be a five-star five-a-side player. In the latest episode of \u2018Barclays WSL Behind the Baller Series 3\u2019, she tells us why small-sided football still gives her a rush unlike anything else.\u2063\n\u2063\nTake to the pitch with your ultimate Aston Villa 5-a-side team in Rush now.",
  "comments": 0,
  "likes": 512,
  "thumbnail": "false",
  "carouselImages": null,
  "url": "https://www.instagram.com/p/DHTLkeXNGc6/",
  "video": true,
  "timestamp": 1742212911,
  "processed": true,
  "__v": 0
}