{
  "_id": {
    "$oid": "681e9882a28b622a39e52642"
  },
  "handle": "realbradthor",
  "shortcode": "DHwAh7WRzcE",
  "caption": "This Independence Day, the stakes are higher than ever. A ruthless conspiracy threatens the nation, and Scot Harvath is the last line of defense. Pre-order EDGE OF HONOR for a pulse-pounding thriller you won\u2019t be able to put down (link in bio).",
  "comments": 11,
  "likes": 289,
  "thumbnail": "false",
  "carouselImages": null,
  "url": "https://www.instagram.com/p/DHwAh7WRzcE/",
  "video": false,
  "timestamp": 1743180158,
  "processed": true,
  "__v": 0
}