{
  "_id": {
    "$oid": "67ef7ecead0be740736a5c58"
  },
  "handle": "dutchbroscoffee",
  "shortcode": "DHYpp2aP2sZ",
  "caption": "Get it poppin\u2019 w/ our blue raz boba \ud83e\udee7\ud83d\udc99\u2063\n\u2063\nAdd it to your Rebel energy drink, lemonade, sparkling soda or tea for bursts of flavor!",
  "comments": 18,
  "likes": 4242,
  "thumbnail": "false",
  "carouselImages": [
    false,
    false
  ],
  "url": "https://www.instagram.com/p/DHYpp2aP2sZ/",
  "video": false,
  "timestamp": 1742396414,
  "processed": true,
  "__v": 0
}