{
  "_id": {
    "$oid": "682988e655b65f59120b9c12"
  },
  "handle": "officialblackwallstreet",
  "shortcode": "DI1v4pRTtwi",
  "caption": "Trailblazers in every sense \ud83d\udc4f\ud83c\udffe Meet Dr. Nicole Foster and Dwight Campbell, the couple behind Cajou Creamery, the first plant-based ice cream shop in Baltimore!\u2060\n\u2060\nFrustrated by the lack of clean, healthy dessert options that celebrated global flavors, they left their careers in medicine and law to build something revolutionary: dairy-free ice cream made with real ingredients and rooted in cultural inspiration.\u2060\n\u2060\n\u2728 Tap the \ud83d\udd17 in bio or in our stories to watch their journey in our latest YouTube video!",
  "comments": 6,
  "likes": 451,
  "thumbnail": "false",
  "carouselImages": null,
  "url": "https://www.instagram.com/p/DI1v4pRTtwi/",
  "video": false,
  "timestamp": 1745520252,
  "processed": true,
  "__v": 0
}