{
  "_id": {
    "$oid": "68289f0b9588a3f3e9a0ad9e"
  },
  "handle": "jerry_taylor_law",
  "shortcode": "DIhfK6qSxZi",
  "caption": "Unfortunately, there\u2019s more to protecting your family, money, and assets, than I can fit in a single post. And everyone has a unique situation. But, I recently created something to fix this:\n\nComment the word \u201cLegacy\u201d and I\u2019ll send you a link where you can get access to everything you need to know about protecting your Legacy, PLUS access to 2 weekly live Q&A calls where you can ask any questions about your specific situation.",
  "comments": 2635,
  "likes": 63205,
  "thumbnail": "false",
  "carouselImages": [
    false,
    false,
    false,
    false,
    false,
    false,
    false
  ],
  "url": "https://www.instagram.com/p/DIhfK6qSxZi/",
  "video": false,
  "timestamp": 1744840389,
  "processed": true,
  "__v": 0
}