{
  "_id": {
    "$oid": "6842df8a9073a9f18eede1b4"
  },
  "handle": "24builds_",
  "shortcode": "DIN95zxiaQz",
  "caption": "Best Seller | The 1802cc German Cruiser. \n\nThis 32cm beast is built from 500+ precision-engineered pieces, bringing heavyweight motorcycle style and function to your hands in 1:8 scale.\n\nInspired by iconic German engineering, the 1802cc Cruiser features functioning steering, shock-absorbing suspension, and a detailed exposed drivetrain\u2014all wrapped in a low-slung frame that screams road presence.\n\nFrom its rubber tyres and ventilated brake discs to its mirrors, mud guards, and rear exhaust, every detail fuels the ride. Build it. Admire it. Rule the road\u2014piece by piece.\n\nOnly at 24builds.com\n\n#buildtheunimaginable #24builds",
  "comments": 4,
  "likes": 126,
  "thumbnail": "false",
  "carouselImages": [
    false,
    false,
    false
  ],
  "url": "https://www.instagram.com/p/DIN95zxiaQz/",
  "video": false,
  "timestamp": 1744185414,
  "processed": true,
  "__v": 0
}