{
  "_id": {
    "$oid": "682824cc65b6996980f2f472"
  },
  "handle": "lomitoperuvianfood",
  "shortcode": "DIorDIbxLii",
  "caption": "Do you take time throughout the day to recalibrate to regroup to refuel? \n\nIf you don\u2019t, you\u2019re doing yourself a disservice. \n\nYou\u2019ve got lunch take lunch get out of the office get some air, go for a walk. \n\nGod forbid something happens to you, you know, there may be some quiet time. Who knows how long? \n\nBut your position will be posted and they will be looking for a replacement. \n\nBest believe that, you can\u2019t help anybody without your body. So take care of the one that you have.",
  "comments": 1,
  "likes": 10,
  "thumbnail": "false",
  "carouselImages": null,
  "url": "https://www.instagram.com/p/DIorDIbxLii/",
  "video": true,
  "timestamp": 1745081529,
  "processed": true,
  "__v": 0
}