{
  "_id": {
    "$oid": "6842dd67ae877a8ee5b45187"
  },
  "handle": "theboilinghouseofcherryhill",
  "shortcode": "DIPMrxzyZQA",
  "caption": "We\u2019re hiring at The Boiling House of Cherry Hill! \ud83e\udd80\ud83c\udf64 Love seafood and working in a fast-paced, fun environment? We\u2019re looking for friendly & motivated servers to join our team!\n\nApply now by sending your resume to: tim@boilinghouse.com\n\u2013\n\ud83d\udccd The Boiling House\n1990 Marlton Pike East, Cherry Hill, NJ\n\n#NowHiring #CherryHillJobs #RestaurantJobs #BoilingHouse #SouthJerseyJobs #PhillyJobs #ServerJobs #JoinOurTeam",
  "comments": 1,
  "likes": 28,
  "thumbnail": "false",
  "carouselImages": null,
  "url": "https://www.instagram.com/p/DIPMrxzyZQA/",
  "video": false,
  "timestamp": 1744226717,
  "processed": true,
  "__v": 0
}