{
  "_id": {
    "$oid": "682833754b9bf0bf39c374a2"
  },
  "handle": "foodnetwork",
  "shortcode": "DIpyZyEP9HN",
  "caption": "\ud83d\udce3 Hate to break it to you, but your food probably needs A LOT more salt!\n\nCatch @chefantonia competing on the #TournamentOfChampions FINALE, Sunday @ 8|7c!",
  "comments": 624,
  "likes": 9610,
  "thumbnail": "false",
  "carouselImages": null,
  "url": "https://www.instagram.com/p/DIpyZyEP9HN/",
  "video": true,
  "timestamp": 1745118919,
  "processed": true,
  "__v": 0
}