{
  "_id": {
    "$oid": "6825e8d95408815724a8ec58"
  },
  "handle": "instatroll_football",
  "shortcode": "DJcSKfuMwzF",
  "caption": "This has got to be the worst thing you can say to Inter legend Javier Zanetti! \ud83d\ude02\ud83d\udc80\n(@giada.bizzarri)\n\n-\n\n#football #soccer #futbol #futebol #calcuo #sport #sports #intermilan #milan #forzamilan",
  "comments": 64,
  "likes": -1,
  "thumbnail": "false",
  "carouselImages": null,
  "url": "https://www.instagram.com/p/DJcSKfuMwzF/",
  "video": true,
  "timestamp": 1746813316,
  "processed": true,
  "__v": 0
}