{
  "_id": {
    "$oid": "68298dfad18362bf0b993c30"
  },
  "handle": "sietefoods",
  "shortcode": "DJDP-GbtACm",
  "caption": "We\u2019ve got a crispy little tip for your next taco night! For the *crrrrunchiest* experience with our NEW Ma\u00edz Corn Taco Shells, we recommend baking them at 375\u00b0F for a **minimum of 5 minutes**. \n\nIf you like your shells extra toasty, you can leave them in for an additional 1\u20132 minutes\u2014just keep a close eye on them so they don\u2019t overcook. \u00a1Buen provecho!\u00a0\u2764\ufe0f\n\n#sietefoods #maiz #maizcorntacoshells #glutenfreemeals #taconight #tacotuesday",
  "comments": 25,
  "likes": 320,
  "thumbnail": "false",
  "carouselImages": null,
  "url": "https://www.instagram.com/p/DJDP-GbtACm/",
  "video": true,
  "timestamp": 1745973350,
  "processed": true,
  "__v": 0
}