{
  "_id": {
    "$oid": "681e1c7472c28b8a5b4123d1"
  },
  "handle": "accenture",
  "shortcode": "DJEmdjEhTrl",
  "caption": "Sound on for good vibes and great coworkers. \ud83d\udc9c\n \n[Video Description: Sequence of shots in an Accenture office. Starts on the terrace, on a sunny day, with the text \u201cSpring in the office without trending audio\u201d. It ends with some interior shots. Follows the trend of showing everyday moments without trending audio].",
  "comments": 4,
  "likes": 613,
  "thumbnail": "false",
  "carouselImages": null,
  "url": "https://www.instagram.com/p/DJEmdjEhTrl/",
  "video": true,
  "timestamp": 1746018600,
  "processed": true,
  "__v": 0
}