{
  "_id": {
    "$oid": "681e337439085622e641511b"
  },
  "handle": "Lakmeindia",
  "shortcode": "DJG0KgytnSC",
  "caption": "Shaadi season\u2019s here and the glam is non-negotiable \ud83d\udc84\u2728\n\nWhether you\u2019re the bride, bridesmaid, or that cousin who always brings main character energy\u2014this shaadi szn, we\u2019ve got you covered. From glowing skin to glam that doesn\u2019t quit,  It\u2019s time to Get Shaadi Ready with Lakm\u0113 \ud83d\udc83\n\nLAKM\u0112\n\n(Lakme, Get Shaadi Ready with Lakme, Wedding Season, Wedding Looks, Bride, Bridal Trends, Make Up)\n\n#Lakme #LakmeIndia #LakmeMakeup  #GSRL #BridalMakeup #ShaadiSeason #GetShaadiReady",
  "comments": 2,
  "likes": 332,
  "thumbnail": "false",
  "carouselImages": null,
  "url": "https://www.instagram.com/p/DJG0KgytnSC/",
  "video": true,
  "timestamp": 1746092943,
  "processed": true,
  "__v": 0
}