{
  "_id": {
    "$oid": "68259f48e1d752ec39b98fb1"
  },
  "handle": "BlueNectar_Ayurved",
  "shortcode": "DJi5ExXClaW",
  "caption": "Guess the active ingredient!\n\n[ plant based skin care , plant based skincare, plant based sunscreen, luxurious ayurveda, coconut sunscreen, eladi sunscreen, eladi spf, shea butter spf 30, face and body spf, oil test, light weight skincare ]\n\n#bluenectar #bluenectar_ayurved #contemporaryayurved #herbquotient #BeBlue_tiful #SavetheBlue #spf #sunscreen #plantbasedskincare #coconutsunscreen #eladispf #summer",
  "comments": 39,
  "likes": 52,
  "thumbnail": "false",
  "carouselImages": null,
  "url": "https://www.instagram.com/p/DJi5ExXClaW/",
  "video": false,
  "timestamp": 1747035010,
  "processed": true,
  "__v": 0
}