{
  "_id": {
    "$oid": "68258ebc697cf8c27727dd63"
  },
  "handle": "GoodRx",
  "shortcode": "DJm8tnJMK_k",
  "caption": "Maybe you\u2019ve experienced delays from a prior authorization, or had to appeal an insurance denial. You\u2019re certainly not alone.\n\nNew research shows that all kinds of insurance are becoming more restrictive. Many medications aren\u2019t covered by plans. And those that are face additional barriers.\n\nClick through to see the impact of catches in prescription plan coverage. \nLearn more at goodrx.co/thebigpinch\n\n#GoodRx #prescriptionsavings #healthcare #health",
  "comments": 0,
  "likes": 9,
  "thumbnail": "false",
  "carouselImages": [
    false,
    false,
    false,
    false
  ],
  "url": "https://www.instagram.com/p/DJm8tnJMK_k/",
  "video": false,
  "timestamp": 1747171136,
  "processed": true,
  "__v": 0
}