{
  "_id": {
    "$oid": "6826568a80ea2504943d9ed2"
  },
  "handle": "theorendatribe",
  "shortcode": "DJo4rusMgeh",
  "caption": "Treasures of the Heart\u2728\ud83d\udc99\nA creative workshop to explore what makes each child unique.\ud83c\udfa8\ud83d\udd8c\ufe0f\n\nFriday, May 23\nThrough art, reflection & joy - we celebrate the treasures within!\ud83c\udfa8\ud83d\udcab\n\n#TreasureOfTheHeart\n#TheOrendaTribe\n\n\ud83d\udcdeBook your place \n0791200818\n\ud83d\udccdThe Orenda Tribe",
  "comments": 4,
  "likes": 15,
  "thumbnail": "false",
  "carouselImages": null,
  "url": "https://www.instagram.com/p/DJo4rusMgeh/",
  "video": true,
  "timestamp": 1747237866,
  "processed": true,
  "__v": 0
}