{
  "_id": {
    "$oid": "682825d00f7dd3159f004912"
  },
  "handle": "casarthakahuja",
  "shortcode": "DJs3ItAS9p_",
  "caption": "Indians are just 1.5% of the US population, at almost 5.1 Mn people... but over 5% of the US taxes are paid by the Indian diaspora... punching far above their weight...\n\n10% of all patents filed in the US have an Indian inventor...\n\n10% of all doctors in the US are of Indian origin... which serve almost 30% of the US patients...\n\nOver 11% of unicorns in the US have an Indian founder...\n\nThey own 60% of all hotels in the US... \n\n70% of the US colleges have an Indian in their top leadership...\n\n78% of Indians in the US have a college degree, far above the national average of 36%... and 76% of these Indians work in positions of management, business, science or arts, not in blue collar work...\n\nOver 80% of the past 30+ Spelling Bee competitions are won by kids from the Indian diaspora\n\nOh, and while Indian restaurants are just 1% of the total restaurants in the US, 3% of all Michelin starred restaurants are Indian... thus, they punch three times above their weight even in culture and food.\n\nIn 2023, these people donated USD 1.5 Bn worth to causes within the US... and almost USD 800 Mn of donations flow from these NRIs to India...\n\nIndians today have so much soft power in the US, and the respect they have earned through generations of hard work is massive.\n\n#casarthakahuja",
  "comments": 299,
  "likes": 21623,
  "thumbnail": "false",
  "carouselImages": null,
  "url": "https://www.instagram.com/p/DJs3ItAS9p_/",
  "video": true,
  "timestamp": 1747369500,
  "processed": true,
  "__v": 0
}