{
  "_id": {
    "$oid": "682789a7980c31dd8dc4167d"
  },
  "handle": "AmaziFoods",
  "shortcode": "DJSj2PdMCZW",
  "caption": "LOADED PLANTAIN CHIP NACHOS FOR CINCO DE MAYO \ud83c\udf89\n\nTalk about a total fiesta for your taste buds!?! \ud83c\udf36\ufe0f\ud83e\uddc0 Double tap if you\u2019re making a batch today! \n\n#CincoDeMayo #Nachos #DriedPlantainChips #NoSugarAdded #GlutenFree #Snacktime #BetterForYou",
  "comments": 4,
  "likes": 14,
  "thumbnail": "false",
  "carouselImages": null,
  "url": "https://www.instagram.com/p/DJSj2PdMCZW/",
  "video": true,
  "timestamp": 1746487084,
  "processed": true,
  "__v": 0
}