{
  "_id": {
    "$oid": "681e21611fb62b4c2000321c"
  },
  "handle": "alvandilawgroup",
  "shortcode": "DJUtMgDvbaa",
  "caption": "If you have to ask, the answer is probably yes. \n\nIf you\u2019ve been injured, call the Alvandi Law Group any time, day or night: (800) 295-4588.",
  "comments": 0,
  "likes": 10,
  "thumbnail": "false",
  "carouselImages": [
    false,
    false,
    false,
    false,
    false
  ],
  "url": "https://www.instagram.com/p/DJUtMgDvbaa/",
  "video": false,
  "timestamp": 1746559018,
  "processed": true,
  "__v": 0
}