{
  "_id": {
    "$oid": "6842d5daa2d1fefd9caf7ff4"
  },
  "handle": "denverlifemagazine",
  "shortcode": "DKcqs8CPprK",
  "caption": "Steamboat\u2019s Yampa Valley Kitchen (@yampavalleykitchen) serves up a recipe for a garden-fresh frittata perfect for lazy brunches, patio picnics, or wherever your statecation takes you. Try the recipe yourself at the link in bio.\u2060\n\u2060\nPhoto Dustin Posiak-Trider\u2060\n#denverlife #denverlifemagazine #denverlifemag #magazine #denver #colorado #recipe #gardenfrittata #frittatarecipe #steamboatrestaurant #steamboat #cooking",
  "comments": 0,
  "likes": 6,
  "thumbnail": "false",
  "carouselImages": null,
  "url": "https://www.instagram.com/p/DKcqs8CPprK/",
  "video": false,
  "timestamp": 1748973647,
  "processed": true,
  "__v": 0
}